{
    "30": "white devil super",
    "2": "Jack Frost nipping nose Silly Squishies",
    "16": "dad Stephanie Student calendar",
    "21": "two kids 1 92",
    "26": "pajamas on. Mulatto watch goodies sleigh go say sister Lisa see reindeer",
    "9": "rise globe find hard sleep",
    "25": "Alice Echo",
    "10": "sleep know laugh",
    "34": "go go gadget",
    "29": "Big Sky Kate Bush killed white devil super",
    "35": "go go gadget Embark OKC many times gotta tell something important",
    "8": "rise globe",
    "6": "help mean Austin use",
    "24": "said many times",
    "4": "elevator",
    "3": "Silly Squishies United elevator",
    "28": "see reindeer really know Big Sky",
    "5": "elevator help mean Austin",
    "23": "said",
    "13": "chassis",
    "14": "every mother's child",
    "31": "devil super",
    "27": "see reindeer really",
    "15": "every mother's child dad",
    "33": "go go gadget",
    "1": "chestnuts roasting open"
}