{
    "377": "world wrong right",
    "148": "wish laying Seattle parking Family schedule",
    "124": "modern world",
    "329": "bad job little bags",
    "241": "master",
    "267": "Amor Freddy Nevada",
    "11": "mango",
    "197": "salamander",
    "215": "hour",
    "136": "Adelphia show Sunset Park Academy September 2nd",
    "382": "house called future attic",
    "55": "1",
    "42": "Santa Rosa Rapunzel watch Madagascar",
    "29": "Ghostbuster games",
    "58": "1 mm",
    "144": "want watch looks shelter mode wanna hear contains like projector",
    "151": "Seattle Family schedule Thursday St. Carlos Marquez Garcia want",
    "239": "status",
    "59": "1 mm",
    "150": "Seattle parking Family schedule Thursday St.",
    "333": "little bags Lies",
    "209": "say",
    "342": "time looking forward Long Beach",
    "344": "forward Long Beach",
    "384": "Laurel,",
    "74": "San Marino Chile",
    "201": "Toyota Venza Venza",
    "236": "Hotel granduca, Dallas",
    "57": "1 mm",
    "111": "Australia Israel",
    "78": "Brazil Bolivia",
    "112": "Australia Israel",
    "205": "Concord Elementary Dragon Express I'll small cup Master cup bad looks.",
    "106": "videos Madea",
    "335": "promise she'll",
    "200": "Toyota Venza Venza",
    "266": "positions triplus Amor Freddy Nevada",
    "388": "tour green dragon",
    "114": "torticollis causes mokenstef",
    "165": "many milligrams Madonna music",
    "219": "hour micronesian Gran",
    "367": "Facebook",
    "223": "micronesian Gran Washington symbol strontium",
    "265": "",
    "269": "Applejack",
    "351": "Brad.",
    "336": "she'll",
    "83": "home Delta Transit jobs",
    "125": "modern world",
    "146": "projector",
    "64": "International Walden Avenue",
    "65": "Avenue",
    "328": "bad job",
    "202": "Venza showed somebody got total drama.",
    "387": "tour green dragon",
    "84": "home Delta Transit jobs",
    "350": "hello, Brad.",
    "394": "Sarah complicated",
    "220": "micronesian Gran Washington",
    "145": "contains like projector",
    "392": "Sarah",
    "127": "modern world",
    "263": "Sunbelt bar exam America",
    "13": "mango salad",
    "346": "",
    "270": "Applejack caramel",
    "86": "use rainbows",
    "126": "modern world",
    "99": "open",
    "141": "eyes projectile Moreno Valley",
    "115": "causes mokenstef",
    "216": "hour micronesian",
    "339": "change time time time",
    "366": "Facebook",
    "77": "San Marino Chile Argentina Brazil Bolivia",
    "80": "Levi rusia Espana",
    "385": "Laurel, Bryan tour",
    "226": "anime persona patient began Chula Vista copied",
    "214": "hour",
    "227": "patient began Chula Vista copied even stop.",
    "82": "home Delta Transit jobs",
    "203": "showed somebody got total drama. speak phone talking Charlene play Kamal",
    "337": "she'll change",
    "75": "San Marino Chile Argentina",
    "60": "1",
    "147": "",
    "195": "animal salamander",
    "332": "job little bags Lies",
    "334": "little bags Lies promise she'll",
    "352": "Brad.",
    "87": "use rainbows",
    "237": "Dallas like status",
    "244": "know going throw",
    "264": "Sunbelt exam America",
    "348": "hello, Brad.",
    "379": "wrong right",
    "381": "",
    "386": "Laurel, Bryan tour green dragon",
    "376": "world",
    "221": "micronesian Gran Washington",
    "198": "salamander",
    "238": "status",
    "153": "want want buddy.",
    "345": "Beach",
    "347": "hello, Brad.",
    "217": "hour micronesian",
    "79": "Brazil Bolivia Levi rusia Espana",
    "152": "Marquez Garcia want want buddy.",
    "272": "1010 sunset Houston",
    "330": "bad job little bags",
    "383": "house called future attic",
    "120": "mean show Salvadorian",
    "113": "Australia Israel",
    "225": "Celestino's Motorsport important physics",
    "76": "San Marino Chile Argentina",
    "224": "Celestino's Motorsport important",
    "12": "mango",
    "242": "know going throw",
    "340": "change time time time",
    "213": "hour",
    "100": "open",
    "343": "looking forward Long Beach",
    "81": "Levi rusia Espana",
    "122": "play sibelius Manning",
    "140": "butthole eyes projectile Moreno Valley",
    "143": "want watch looks shelter mode wanna",
    "107": "videos Madea",
    "204": "play Kamal Concord Elementary",
    "196": "animal salamander",
    "208": "say",
    "393": "Sarah Warehouse",
    "341": "time time time looking forward Long Beach",
    "268": "Freddy Nevada",
    "378": "wrong right",
    "389": "green dragon",
    "240": "master",
    "73": "San Marino",
    "243": "know going throw",
    "262": "I'll talk talk somebody. Sunbelt bar exam",
    "380": "much say",
    "156": "interesting 1:11",
    "222": "micronesian Gran Washington",
    "123": "sibelius Manning interested modern world",
    "261": "I'll talk talk somebody.",
    "72": "San",
    "271": "Advanced Animal Park",
    "338": "change time time time",
    "149": "wish laying Seattle parking Family schedule Thursday",
    "349": "hello, Brad.",
    "27": "new Punjabi Dhaba look post Malone",
    "331": "bad job little bags Lies",
    "218": "hour micronesian Gran",
    "56": "1 mm",
    "108": "Madea",
    "41": "video Drama TV Bianca Santa Rosa"
}