{
    "148": "fun",
    "89": "Isabella",
    "288": "everytime",
    "267": "",
    "360": "beverages",
    "197": "cheers",
    "158": "like",
    "215": "said want say know way want",
    "136": "I'll go get ring let choir Bells sing",
    "160": "like ready cuz beautiful",
    "382": "sheep",
    "207": "song",
    "209": "cheers",
    "342": "glass",
    "173": "said",
    "344": "glass goes",
    "289": "everytime School",
    "356": "beverages",
    "384": "sheep",
    "201": "young",
    "435": "sent",
    "139": "sing",
    "185": "",
    "111": "",
    "90": "Isabella",
    "159": "like ready cuz beautiful",
    "112": "",
    "175": "said",
    "106": "trash got Pocketful cash",
    "212": "know things want know",
    "266": "",
    "433": "sent",
    "121": "black umbrella cuz beautiful",
    "114": "",
    "109": "cash buy",
    "355": "beverages",
    "223": "Shih Tzu",
    "265": "",
    "269": "ran away",
    "351": "heavy",
    "135": "I'll go get ring let",
    "354": "beverages",
    "434": "sent",
    "202": "young",
    "138": "sing",
    "350": "heavy",
    "292": "School",
    "357": "beverages",
    "346": "glass goes gets",
    "270": "ran",
    "137": "go get ring let choir Bells sing",
    "290": "everytime School",
    "216": "said want say know way want play",
    "105": "trash got Pocketful",
    "206": "song",
    "385": "sheep",
    "211": "know things want know",
    "214": "know said",
    "226": "song",
    "227": "song",
    "359": "beverages",
    "147": "fun",
    "379": "sheep",
    "432": "sent",
    "104": "",
    "352": "",
    "381": "sheep",
    "348": "glass goes gets heavy",
    "345": "glass goes gets",
    "347": "glass goes gets heavy",
    "217": "say know way want play",
    "383": "sheep",
    "120": "black umbrella cuz beautiful",
    "113": "",
    "225": "Battlefield song",
    "184": "",
    "224": "Battlefield song",
    "213": "know things want know",
    "343": "glass goes",
    "122": "beautiful",
    "291": "everytime School",
    "107": "trash got Pocketful cash buy",
    "361": "beverages",
    "208": "song cheers",
    "174": "said",
    "161": "beautiful",
    "186": "",
    "378": "",
    "88": "Isabella",
    "380": "sheep",
    "149": "fun",
    "358": "beverages",
    "349": "glass goes gets heavy",
    "218": "know way want play",
    "108": "got Pocketful cash buy"
}