{
    "148": "road go",
    "46": "MattyB",
    "158": "dumb",
    "25": "eBay",
    "151": "road go",
    "29": "Anson belt",
    "144": "",
    "155": "dumb",
    "150": "road go",
    "20": "play",
    "194": "come walking",
    "112": "eBay",
    "175": "darling",
    "114": "eBay",
    "187": "darling come walking animal",
    "146": "road go",
    "49": "MattyB",
    "145": "road",
    "192": "animal",
    "45": "MattyB",
    "117": "eBay",
    "105": "baby",
    "115": "eBay",
    "47": "MattyB",
    "50": "MattyB",
    "101": "baby",
    "190": "come animal",
    "188": "come walking animal",
    "147": "road go",
    "157": "dumb",
    "104": "baby",
    "103": "baby",
    "153": "go",
    "152": "go",
    "118": "eBay",
    "120": "eBay",
    "154": "dumb",
    "48": "MattyB",
    "113": "eBay",
    "100": "baby",
    "189": "come walking animal",
    "21": "play Asia go play Keyshia Cole",
    "102": "baby",
    "51": "MattyB",
    "22": "play Keyshia Cole",
    "24": "eBay",
    "119": "eBay",
    "191": "animal",
    "156": "dumb",
    "116": "eBay",
    "149": "road go",
    "23": "play Keyshia Cole eBay"
}