{
    "30": "set come find Hobby Lobby Peabody mobile Nello's Cafe videography turn gaming unit going answer that's",
    "33": "Indian galipeau Plaza",
    "32": "picture Indian galipeau Vista Plaza",
    "16": "okay Moto thing said kefir Mondo Liberty Tony pajamas",
    "11": "Andy got Mindy Letterman today International Queenie amnesty CA politician",
    "21": "Lamb God manga character liquor store Boston Tea Party",
    "26": "Mitchell Pavilion mall Pensacola Bob Kenya local time La quesadilla Mexican",
    "9": "La Vista Bonita",
    "25": "questions domestic uniform Macy's Makati give spell Malachi",
    "34": "galipeau Plaza",
    "29": "restore Nicolas Batum Peppa Pig minipro Madonna Ghana capital BC set",
    "19": "Alpha Martin ecoquest 220v Le Bambini Mariano YouTube al pastor",
    "17": "fruity nostril Horus eBay hoping want come gone day I'll get get food give Armando Montelongo Santa. Can",
    "8": "call Yellow Cab okay Newton International Controla La Vista",
    "22": "Nikita Channel 4 people cannot get name liquor store lady actually good dematic principal",
    "6": "questions",
    "24": "millimeter automatic creamy liquid solid Aquarius daily sodium intake",
    "4": "millimeter requests questions",
    "3": "millimeter requests",
    "28": "dentist restore",
    "5": "millimeter requests questions",
    "20": "al pastor yesterday Culligan Anthology resume Lamb God manga",
    "23": "fuck three mathematical images tell millimeter automatic",
    "14": "number request Campagna Monkey that's Tonto started Columbia Gas",
    "31": "going answer that's stop. Lamborghini Murcielago",
    "27": "La quesadilla Mexican animals images onion loaf Beauty Magnolia, cancel thought thought go love dentist restore",
    "15": "blank let see foxy 1 Persona 21 door",
    "12": "Uncle Charlie missed Best Western Universal",
    "18": "get get food give Armando Montelongo Santa. Can PC makers Zone salmon represent Logan Utah Alpha Martin"
}