{
    "30": "look big door buzzer",
    "54": "Shack Shack",
    "32": "look big door buzzer",
    "50": "conversations",
    "62": "police",
    "55": "Shack",
    "102": "Frozen Let It Go",
    "29": "look big door",
    "64": "police",
    "51": "conversations versus sting",
    "53": "sting Shack Shack",
    "103": "Frozen Let It Go",
    "72": "kung fu",
    "57": "cousin reality",
    "71": "kung fu",
    "63": "police",
    "31": "look big door buzzer",
    "56": "cousin",
    "52": "versus sting Shack Shack",
    "33": "big door buzzer"
}