{
    "2": "might hard believe",
    "16": "waves untouched Coastline II tonight",
    "11": "tourist love seeing new place love going California one favorite spots",
    "7": "might hard believe years still love traveling love tourist love seeing new place",
    "9": "still love traveling love tourist love seeing new place",
    "10": "love tourist love seeing new place love going",
    "17": "II tonight",
    "8": "still love traveling love tourist love seeing new place",
    "6": "might hard believe years still love traveling love",
    "4": "might hard believe years still love",
    "3": "might hard believe years still",
    "5": "might hard believe years still love traveling",
    "13": "California one favorite spots wind waves untouched Coastline II tonight",
    "14": "waves untouched Coastline II tonight",
    "15": "waves untouched Coastline II tonight",
    "12": "new love going California one favorite spots wind waves untouched"
}