{
    "47": "glycine",
    "54": "Nitro",
    "50": "glycine",
    "68": "shows",
    "16": "lysine said nothing say nothing",
    "62": "massage",
    "46": "glycine",
    "7": "face everyday Sirens calling",
    "9": "calling",
    "43": "glycine",
    "55": "Nitro massage",
    "42": "Frozen cheesecake",
    "60": "massage",
    "58": "Nitro massage",
    "19": "Rosa's Cafe",
    "59": "Nitro massage",
    "8": "face Sirens calling",
    "49": "glycine",
    "6": "see face everyday",
    "44": "glycine",
    "4": "heading",
    "3": "time heading",
    "61": "massage",
    "5": "see",
    "57": "Nitro massage",
    "20": "Cafe",
    "45": "glycine",
    "13": "search emojis cat",
    "67": "shows",
    "48": "glycine",
    "56": "Nitro massage",
    "15": "much phone",
    "12": "search"
}