{
    "68": "what's",
    "11": "bus league crew",
    "39": "man",
    "46": "",
    "134": "favorite",
    "197": "beginner wakeboards",
    "55": "yes ask",
    "42": "guy",
    "58": "",
    "131": "what's favorite",
    "59": "",
    "8": "Tulsa bus league",
    "199": "8 Asbury tell teacher word search",
    "74": "what's favorite",
    "201": "tell teacher word search",
    "185": "Ventura County",
    "57": "",
    "20": "feature",
    "14": "league crew",
    "70": "what's favorite",
    "106": "scary bed never ever seen",
    "52": "yes ask",
    "18": "league feature",
    "200": "Asbury tell teacher word search",
    "69": "what's favorite",
    "165": "what's favorite",
    "223": "Surfin USA",
    "166": "what's favorite",
    "133": "favorite",
    "187": "County",
    "135": "favorite",
    "17": "league crew",
    "202": "tell teacher word search",
    "44": "",
    "4": "Tulsa",
    "37": "man",
    "220": "Urban USA everybody",
    "45": "",
    "168": "what's favorite",
    "13": "league crew",
    "105": "scary bed",
    "115": "what's favorite",
    "47": "",
    "54": "yes ask",
    "50": "yes",
    "40": "man guy",
    "190": "Surfin USA",
    "226": "Surfin USA",
    "227": "Surfin USA",
    "7": "Tulsa bus",
    "9": "bus league crew",
    "43": "",
    "75": "favorite",
    "132": "favorite",
    "203": "tell word search",
    "104": "scary",
    "221": "everybody",
    "198": "beginner wakeboards Super 8 Asbury tell teacher",
    "217": "Surfin USA",
    "38": "man",
    "71": "what's favorite",
    "36": "come man",
    "225": "Surfin USA",
    "76": "favorite",
    "184": "USA Everybody California using",
    "12": "bus league crew",
    "224": "Surfin USA",
    "167": "what's favorite",
    "16": "league crew",
    "107": "never ever seen",
    "21": "feature",
    "10": "bus league crew",
    "161": "what's favorite",
    "19": "feature",
    "162": "what's favorite",
    "186": "Ventura County",
    "51": "yes",
    "22": "feature",
    "6": "Tulsa bus",
    "73": "what's favorite",
    "191": "Surfin USA",
    "53": "yes ask",
    "72": "what's favorite",
    "5": "Tulsa bus",
    "163": "",
    "56": "yes ask",
    "164": "what's favorite",
    "41": "guy",
    "15": "league crew"
}