{
    "7": "Denny's East-West Center",
    "4": "Indian Shakira Uncle Bob",
    "9": "want fun party pool Secret John kopke chewy spice",
    "10": "spice",
    "2": "Angus beef OK Google DC Lottery results",
    "3": "results song Cinema cellulitis Boise Mall Indian booty",
    "5": "7076 Justin Bieber song Grandma cookies tantrum Grove area",
    "8": "physical theme tune solar array sequence create mask use total discretion want fun party pool",
    "6": "Grandma cookies tantrum Grove area sickness Watchers, cheesy 6th July",
    "1": "let's go let's go quick memo Google Google Google Google"
}