{
    "47": "love",
    "68": "Jaguar XF",
    "69": "enhance",
    "80": "colossal squid",
    "81": "colossal squid",
    "62": "song Fox Hound",
    "21": "swimming",
    "46": "love",
    "91": "flies",
    "26": "Sanskrit",
    "25": "laugh",
    "66": "Rising Sun",
    "29": "Sanskrit",
    "19": "swimming",
    "17": "12ft swimming",
    "64": "stop",
    "65": "House Rising Sun",
    "22": "picture Lexus",
    "24": "Lexus laugh",
    "92": "Black",
    "72": "craft",
    "28": "Sanskrit",
    "90": "small black flies",
    "20": "swimming",
    "23": "Lexus",
    "45": "love",
    "13": "Play-Doh stuff",
    "14": "Play-Doh stuff",
    "63": "Fox Hound stop",
    "71": "enhance craft",
    "67": "Jaguar",
    "27": "Sanskrit",
    "93": "Black Flag",
    "70": "enhance craft",
    "94": "Flag",
    "12": "Play-Doh stuff",
    "18": "swimming"
}