{
    "68": "like get know student",
    "89": "offer due starting August engineering college career center help find job",
    "11": "H definitely diverse awesome place go",
    "39": "something experience yes diverse City",
    "46": "think really contributes education living things always",
    "85": "currently internship NASA summer start excited",
    "25": "U H people culture many different types",
    "55": "University Houston working biomedical engineering",
    "42": "yes diverse City",
    "29": "Pot opening popular Ages",
    "58": "specific play drug-delivery System uh lot research",
    "66": "smart",
    "59": "specific play drug-delivery System uh lot research opportunities",
    "74": "want feel home want feel like felt Cullen",
    "95": "set opportunities bacone College Engineering offer us well",
    "57": "biomedical engineering applications specific play drug-delivery System",
    "20": "dad went engineering college familiar anything",
    "90": "college career center help find job process sheared alumni",
    "111": "enjoy U H Houston answered perspective",
    "14": "portable visited U H senior high school great experience interacting professors",
    "31": "opening popular Ages gotten much larger first started coming there's",
    "78": "felt Cullen College Engineering that's chose",
    "112": "Houston answered perspective",
    "70": "like get know student like come office like conversations time ask life",
    "106": "swing work hard try fun",
    "33": "gotten much larger first started coming there's always something new",
    "18": "cilities ate community-oriented dad went engineering college",
    "52": "organizing events sorority dancing there's many opportunities",
    "121": "city country",
    "69": "like get know student like come office like",
    "114": "we're working towards something towards goal many",
    "109": "fun spend much time enjoy U H",
    "96": "bacone College Engineering offer us well positioned graduate really",
    "26": "people culture many different types Melting Pot",
    "35": "larger first started coming there's always something new going something fun",
    "83": "graduated going continue research currently internship",
    "17": "professors cilities ate community-oriented dad went",
    "64": "machine design system getting professors guys smart",
    "65": "getting professors guys smart",
    "49": "U H there's much going busy student",
    "44": "City perspective think really",
    "84": "currently internship NASA",
    "4": "see class",
    "37": "new something fun experience yes diverse",
    "110": "much time enjoy U H Houston answered",
    "45": "perspective think really contributes",
    "13": "place go church close home portable visited U H senior high",
    "86": "internship NASA summer start excited we're going return offer due",
    "117": "towards goal many opportunities best school Texas would text soon",
    "99": "support group",
    "93": "alumni work right Houston great set",
    "94": "work right Houston great set opportunities bacone",
    "105": "roof agree help try swing work hard",
    "30": "opening popular Ages gotten",
    "115": "working towards something towards goal many opportunities",
    "47": "education living things always happening U H there's",
    "54": "dancing there's many opportunities students University Houston working",
    "32": "gotten much larger first started coming there's always",
    "50": "there's much going busy student organizing events",
    "77": "felt Cullen College Engineering that's chose",
    "40": "experience yes diverse City",
    "80": "College Engineering that's chose graduated going continue",
    "101": "support group energy going roof agree",
    "82": "chose graduated going continue research currently",
    "91": "center help find job process sheared alumni base work right",
    "7": "Miss Lady",
    "9": "would say H",
    "43": "yes diverse City",
    "60": "drug-delivery System lot research opportunities specific focus",
    "34": "larger first started coming there's always something new going",
    "75": "home want like felt Cullen College Engineering",
    "104": "going roof agree help try",
    "87": "summer start excited we're going return offer due starting August",
    "103": "support group energy going roof agree help",
    "3": "see class",
    "61": "lot opportunities specific focus Engineering",
    "79": "felt Cullen College Engineering that's chose graduated going",
    "38": "something fun experience yes diverse",
    "118": "best school Texas would text soon",
    "71": "like come office like conversations time ask life studies",
    "120": "would text soon city country",
    "36": "started coming there's always something new going something fun experience yes",
    "48": "things always happening U H there's much going",
    "113": "answered perspective we're working towards something",
    "76": "felt Cullen College Engineering that's chose",
    "12": "awesome place go church close",
    "100": "support group energy going",
    "81": "that's chose graduated going continue research",
    "98": "graduate really thankful go",
    "16": "experience interacting professors cilities ate community-oriented",
    "62": "opportunities specific focus Engineering time",
    "107": "hard try fun spend much time enjoy",
    "21": "engineering college familiar anything one",
    "10": "would say H definitely diverse",
    "102": "support group energy going roof agree",
    "19": "community-oriented dad went engineering college familiar",
    "51": "busy student organizing events sorority dancing",
    "22": "anything one largest cities nation Houston favorite part",
    "6": "Miss Lady",
    "24": "favorite part U H people",
    "73": "ask studies want feel home want feel like",
    "88": "we're going return offer due starting August engineering college",
    "92": "process alumni base work right Houston great",
    "119": "best Texas would text soon city country",
    "53": "sorority dancing there's many opportunities students University",
    "116": "towards something towards goal many opportunities best school",
    "72": "like conversations time ask life studies want feel home want feel like",
    "28": "Melting Pot opening popular Ages",
    "5": "see",
    "23": "cities nation Houston favorite part U H",
    "63": "focus Engineering time machine design system getting professors",
    "27": "Melting Pot opening popular",
    "56": "working biomedical engineering applications specific play",
    "97": "Engineering us well positioned graduate really really thankful",
    "108": "try fun spend much time enjoy U",
    "41": "experience yes diverse City",
    "15": "great experience interacting professors cilities ate"
}